brawl_stars_brawler_maker/__init__.py
brawl_stars_brawler_maker/brawler_maker.py
brawl_stars_brawler_maker/projectiles.py
brawl_stars_brawler_maker/rarities.py
brawl_stars_brawler_maker/speeds.py
brawl_stars_brawler_maker/default_files/csv_logic/accessories.csv
brawl_stars_brawler_maker/default_files/csv_logic/alliance_badges.csv
brawl_stars_brawler_maker/default_files/csv_logic/alliance_roles.csv
brawl_stars_brawler_maker/default_files/csv_logic/area_effects.csv
brawl_stars_brawler_maker/default_files/csv_logic/bosses.csv
brawl_stars_brawler_maker/default_files/csv_logic/campaign.csv
brawl_stars_brawler_maker/default_files/csv_logic/cards.csv
brawl_stars_brawler_maker/default_files/csv_logic/challenges.csv
brawl_stars_brawler_maker/default_files/csv_logic/characters.csv
brawl_stars_brawler_maker/default_files/csv_logic/emotes.csv
brawl_stars_brawler_maker/default_files/csv_logic/game_mode_variations.csv
brawl_stars_brawler_maker/default_files/csv_logic/globals.csv
brawl_stars_brawler_maker/default_files/csv_logic/items.csv
brawl_stars_brawler_maker/default_files/csv_logic/locales.csv
brawl_stars_brawler_maker/default_files/csv_logic/location_themes.csv
brawl_stars_brawler_maker/default_files/csv_logic/locations.csv
brawl_stars_brawler_maker/default_files/csv_logic/map_blocks.csv
brawl_stars_brawler_maker/default_files/csv_logic/maps.csv
brawl_stars_brawler_maker/default_files/csv_logic/messages.csv
brawl_stars_brawler_maker/default_files/csv_logic/milestones.csv
brawl_stars_brawler_maker/default_files/csv_logic/name_colors.csv
brawl_stars_brawler_maker/default_files/csv_logic/pins.csv
brawl_stars_brawler_maker/default_files/csv_logic/player_thumbnails.csv
brawl_stars_brawler_maker/default_files/csv_logic/projectiles.csv
brawl_stars_brawler_maker/default_files/csv_logic/regions.csv
brawl_stars_brawler_maker/default_files/csv_logic/resources.csv
brawl_stars_brawler_maker/default_files/csv_logic/skills.csv
brawl_stars_brawler_maker-1.0.8.dist-info/LICENSE
brawl_stars_brawler_maker-1.0.8.dist-info/METADATA
brawl_stars_brawler_maker-1.0.8.dist-info/WHEEL
brawl_stars_brawler_maker-1.0.8.dist-info/top_level.txt
brawl_stars_brawler_maker-1.0.8.dist-info/RECORD
