Metadata-Version: 2.1
Name: brawl-stars-brawler-maker
Version: 1.0.8
Summary: A package to mod Brawl Stars game files for custom brawler creation.
Home-page: https://github.com/AngelFireLA/Brawler-Maker-Python-Library
Author: AngelFire
Classifier: Programming Language :: Python :: 3
Classifier: License :: OSI Approved :: MIT License
Classifier: Operating System :: OS Independent
Requires-Python: >=3.7
License-File: LICENSE
Requires-Dist: apk-signer
Requires-Dist: tenacity
Requires-Dist: tqdm
Requires-Dist: pycryptodome
